odoo10_addon_stock_picking_completion_info-10.0.1.1.1-py3.8-nspkg.pth
odoo/addons/stock_picking_completion_info/README.rst
odoo/addons/stock_picking_completion_info/__init__.py
odoo/addons/stock_picking_completion_info/__manifest__.py
odoo/addons/stock_picking_completion_info/i18n/stock_picking_completion_info.pot
odoo/addons/stock_picking_completion_info/models/__init__.py
odoo/addons/stock_picking_completion_info/models/stock_picking.py
odoo/addons/stock_picking_completion_info/readme/CONTRIBUTORS.rst
odoo/addons/stock_picking_completion_info/readme/DESCRIPTION.rst
odoo/addons/stock_picking_completion_info/static/description/icon.png
odoo/addons/stock_picking_completion_info/static/description/index.html
odoo/addons/stock_picking_completion_info/tests/__init__.py
odoo/addons/stock_picking_completion_info/tests/test_stock_picking_completion_info.py
odoo/addons/stock_picking_completion_info/views/stock_picking.xml
odoo10_addon_stock_picking_completion_info-10.0.1.1.1.dist-info/METADATA
odoo10_addon_stock_picking_completion_info-10.0.1.1.1.dist-info/WHEEL
odoo10_addon_stock_picking_completion_info-10.0.1.1.1.dist-info/namespace_packages.txt
odoo10_addon_stock_picking_completion_info-10.0.1.1.1.dist-info/top_level.txt
odoo10_addon_stock_picking_completion_info-10.0.1.1.1.dist-info/RECORD
