Metadata-Version: 2.1
Name: odoo10-addon-stock-picking-completion-info
Version: 10.0.1.1.1
Summary: Display on current document completion information according to next operations
Home-page: https://github.com/OCA/stock-logistics-warehouse
Author: Camptocamp, Odoo Community Association (OCA)
Author-email: support@odoo-community.org
License: AGPL-3
Platform: UNKNOWN
Classifier: Programming Language :: Python
Classifier: Framework :: Odoo
Classifier: Framework :: Odoo :: 10.0
Classifier: License :: OSI Approved :: GNU Affero General Public License v3
Classifier: Development Status :: 3 - Alpha
Requires-Python: ~=2.7
Requires-Dist: odoo10-addon-stock-move-common-dest
Requires-Dist: odoo (<10.1dev,>=10.0)
